LICENSE
MANIFEST.in
README.md
setup.py
cnps/__init__.py
cnps/cli.py
cnps/dump.py
cnps/filter.py
cnps/user.py
cnps.egg-info/PKG-INFO
cnps.egg-info/SOURCES.txt
cnps.egg-info/dependency_links.txt
cnps.egg-info/entry_points.txt
cnps.egg-info/not-zip-safe
cnps.egg-info/requires.txt
cnps.egg-info/top_level.txt
requirements/common.txt
requirements/development.txt
requirements/test.txt